cipher_ky2458/__init__.py
cipher_ky2458/cipher_ky2458.py
cipher_ky2458-0.1.1.dist-info/LICENSE
cipher_ky2458-0.1.1.dist-info/WHEEL
cipher_ky2458-0.1.1.dist-info/METADATA
cipher_ky2458-0.1.1.dist-info/RECORD
