Metadata-Version: 2.1
Name: cipher-ky2458
Version: 0.1.1
Summary: Each letter is replaced by a letter some fixed number of positions down the alphabet.
Home-page: https://github.com/QMSS-G5072-2021/cipher_kun_yao
License: MIT
Author: Kun Yao
Requires-Python: >=3.9,<4.0
Classifier: License :: OSI Approved :: MIT License
Classifier: Programming Language :: Python :: 3
Classifier: Programming Language :: Python :: 3.10
Classifier: Programming Language :: Python :: 3.9
Requires-Dist: pandas (>=1.3.4,<2.0.0)
Project-URL: Documentation, https://cipher-kun-yao.readthedocs.io/en/latest/
Project-URL: Repository, https://github.com/QMSS-G5072-2021/cipher_kun_yao
